caqtus_devices/pulse_generators/spincore_pulse_blaster/__init__.py
caqtus_devices/pulse_generators/spincore_pulse_blaster/_compiler.py
caqtus_devices/pulse_generators/spincore_pulse_blaster/_extension.py
caqtus_devices/pulse_generators/spincore_pulse_blaster/py.typed
caqtus_devices/pulse_generators/spincore_pulse_blaster/configuration/__init__.py
caqtus_devices/pulse_generators/spincore_pulse_blaster/configuration/configuration.py
caqtus_devices/pulse_generators/spincore_pulse_blaster/configuration_editor/__init__.py
caqtus_devices/pulse_generators/spincore_pulse_blaster/configuration_editor/editor.py
caqtus_devices/pulse_generators/spincore_pulse_blaster/runtime/__init__.py
caqtus_devices/pulse_generators/spincore_pulse_blaster/runtime/runtime.py
caqtus_devices/pulse_generators/spincore_pulse_blaster/runtime/spinapi.py
caqtus_devices_spincore_pulse_blaster-1.14.1.dist-info/METADATA
caqtus_devices_spincore_pulse_blaster-1.14.1.dist-info/WHEEL
caqtus_devices_spincore_pulse_blaster-1.14.1.dist-info/licenses/license.md
caqtus_devices_spincore_pulse_blaster-1.14.1.dist-info/RECORD
