Metadata-Version: 2.4
Name: caqtus-devices-spincore-pulse-blaster
Version: 1.14.1
Summary: Contains the caqtus device extension for the Spincore PulseBlaster pulse generator.
Author-email: light-scattering-io <lecaqtus66@gmail.com>
License: Copyright 2024 Université Paris-Saclay
License-File: license.md
Requires-Python: >=3.12
Requires-Dist: caqtus-suite>=6.18.1
